{
    "Thermal-Impedance-analyzer": {
      "title": "Reliability Engineering in Braking Systems",
      "description": "This is the first project.",
      "image": "../../assets/images/esp.gif"
    },
    "Social-Navigation": {
      "title": "Social Navigation using Deep Reinforcement Learning",
      "description": "This is the second project.",
      "image": "../../assets/images/social_navigation.webp"
    },
    "Mini-PLC": {
      "title": "Mini-PLC using OpenPLC",
      "description": "This is the fourth project.",
      "video": "../../assets/videos/MiniPLC.mp4"
    },
    "Package-Sorting": {
      "title": "Package Sorting using Siemens PLC",
      "description": "This is the fifth project.",
      "video": "../../assets/videos/Transportmodell.mp4"
    },
    "HMI-and-Connected-Mobility": {
      "title": "HMI and Connected Mobility",
      "description": "This is the sixth project.",
      "image": "../../assets/images/connected-mobility.gif"
    },
    "Electric-Vehicle-Range-Prediction": {
      "title": "Electric Vehicles Range Prediction",
      "description": "This is the third project.",
      "video": "../../assets/videos/supervised-learning.mp4"
    }
  }
  